allure_docx/__init__.py
allure_docx/commandline.py
allure_docx/config.py
allure_docx/report_builder.py
allure_docx/template.docx
allure_docx/config/compact.ini
allure_docx/config/no_trace.ini
allure_docx/config/standard.ini
allure_docx/config/standard_on_fail.ini
allure_docx-0.4.0.dist-info/LICENSE
allure_docx-0.4.0.dist-info/METADATA
allure_docx-0.4.0.dist-info/WHEEL
allure_docx-0.4.0.dist-info/entry_points.txt
allure_docx-0.4.0.dist-info/top_level.txt
allure_docx-0.4.0.dist-info/RECORD
