Metadata-Version: 2.1
Name: allure-docx
Version: 0.4.0
Summary: Docx report generator based on allure-generated json files.
Author: Victor Maryama (Typhoon HIL, Inc), Bjarne Scheimann (Fraunhofer Institute for Solar Energy Systems ISE)
License: MIT
Project-URL: Source, https://github.com/typhoon-hil/allure-docx
Project-URL: Tracker, https://github.com/typhoon-hil/allure-docx/issues
License-File: LICENSE
Requires-Dist: setuptools-git (~=1.2)
Requires-Dist: matplotlib (<4.0,>=3.0)
Requires-Dist: docx2pdf (~=0.1.8)
Requires-Dist: click
Requires-Dist: python-docx
Provides-Extra: dev
Requires-Dist: pyinstaller ; extra == 'dev'
